ust_gen/__init__.py
ust_gen/cli.py
ust_gen/file_parser.py
ust_gen/interface.py
ust_gen/test.py
ust_gen/generator/__init__.py
ust_gen/generator/story_generator.py
ust_gen/utils/__init__.py
ust_gen/utils/azure_openai.py
ust_gen-0.2.3.dist-info/METADATA
ust_gen-0.2.3.dist-info/WHEEL
ust_gen-0.2.3.dist-info/top_level.txt
ust_gen-0.2.3.dist-info/RECORD
